{
  "id": "hero",
  "type": "SharedSlice",
  "name": "Hero",
  "description": "Hero",
  "variations": [
    {
      "id": "default",
      "name": "Default",
      "docURL": "...",
      "version": "initial",
      "description": "Default",
      "imageUrl": "",
      "primary": {
        "hero_image": {
          "type": "Image",
          "config": {
            "label": "Hero Image",
            "constraint": {},
            "thumbnails": []
          }
        },
        "title": {
          "type": "Text",
          "config": {
            "label": "Title",
            "placeholder": "Americanto"
          }
        },
        "right_text": {
          "type": "Text",
          "config": {
            "label": "Right Text",
            "placeholder": ""
          }
        },
        "left_text": {
          "type": "Text",
          "config": {
            "label": "Left Text",
            "placeholder": ""
          }
        }
      },
      "items": {}
    }
  ]
}